mlpype/xgboost/__init__.py
mlpype/xgboost/model/__init__.py
mlpype/xgboost/model/xgboost_model.py
mlpype_xgboost-0.6.12.dist-info/METADATA
mlpype_xgboost-0.6.12.dist-info/WHEEL
mlpype_xgboost-0.6.12.dist-info/RECORD
